{
  "contacts": [
    {
      "fullname": "جواد مولایی۲",
      "photo": "https://encrypted-tbn0.gstatic.com/images?q=tbn:ANd9GcTTG3iMTi5x1MHKQvmVLR8_GsBb81rUGgBBAQ&usqp=CAU",
      "mobile": 9019183099,
      "email": "ijavadmoulaei@gmail.com",
      "job": "برنامه نویس",
      "group": "1",
      "id": 3
    }
  ],
  "groups": [
    {
      "id": "1",
      "name": "همکار"
    },
    {
      "id": "2",
      "name": "دوست"
    },
    {
      "id": "3",
      "name": "فامیل"
    },
    {
      "id": "4",
      "name": "سرویس"
    },
    {
      "id": "5",
      "name": "آشنا"
    }
  ]
}